dataform_viz/__init__.py
dataform_viz/cleanup.py
dataform_viz/cli.py
dataform_viz/dataform_check.py
dataform_viz/master_index.py
dataform_viz/parser.py
dataform_viz/svg_generator.py
dataform_viz/visualizer.py
dataform_dependency_visualizer-0.2.4.dist-info/entry_points.txt
dataform_dependency_visualizer-0.2.4.dist-info/licenses/LICENSE
dataform_dependency_visualizer-0.2.4.dist-info/METADATA
dataform_dependency_visualizer-0.2.4.dist-info/WHEEL
dataform_dependency_visualizer-0.2.4.dist-info/RECORD
