Metadata-Version: 2.4
Name: dataform-dependency-visualizer
Version: 0.2.4
Summary: Visualize Dataform table dependencies as interactive SVG diagrams
License: MIT
License-File: LICENSE
Keywords: dataform,dependencies,visualization,bigquery,sql
Author: Thamo
Author-email: thamo@example.com
Requires-Python: >=3.10,<4.0
Classifier: Development Status :: 4 - Beta
Classifier: Intended Audience :: Developers
Classifier: License :: OSI Approved :: MIT License
Classifier: Programming Language :: Python :: 3
Classifier: Programming Language :: Python :: 3.10
Classifier: Programming Language :: Python :: 3.11
Classifier: Programming Language :: Python :: 3.12
Classifier: Programming Language :: Python :: 3.13
Classifier: Programming Language :: Python :: 3.14
Classifier: Topic :: Database
Classifier: Topic :: Software Development :: Libraries :: Python Modules
Project-URL: Homepage, https://github.com/OshigeAkito/dataform-dependency-visualizer
Project-URL: Repository, https://github.com/OshigeAkito/dataform-dependency-visualizer
